odoo9_addon_crm_rma_location-9.0.1.0.0-py2.7-nspkg.pth
odoo_addons/crm_rma_location/__openerp__.py
odoo_addons/crm_rma_location/__init__.py
odoo_addons/crm_rma_location/README.rst
odoo_addons/crm_rma_location/models/stock_warehouse.py
odoo_addons/crm_rma_location/models/__init__.py
odoo_addons/crm_rma_location/i18n/es.po
odoo_addons/crm_rma_location/i18n/crm_rma_location_rma.pot
odoo_addons/crm_rma_location/i18n/sl.po
odoo_addons/crm_rma_location/i18n/de.po
odoo_addons/crm_rma_location/i18n/fr.po
odoo_addons/crm_rma_location/i18n/pt_BR.po
odoo_addons/crm_rma_location/i18n/es_VE.po
odoo_addons/crm_rma_location/i18n/es_MX.po
odoo_addons/crm_rma_location/i18n/es_PA.po
odoo_addons/crm_rma_location/views/stock_warehouse.xml
odoo_addons/crm_rma_location/tests/test_location_rma.py
odoo_addons/crm_rma_location/tests/__init__.py
odoo9_addon_crm_rma_location-9.0.1.0.0.dist-info/top_level.txt
odoo9_addon_crm_rma_location-9.0.1.0.0.dist-info/WHEEL
odoo9_addon_crm_rma_location-9.0.1.0.0.dist-info/RECORD
odoo9_addon_crm_rma_location-9.0.1.0.0.dist-info/metadata.json
odoo9_addon_crm_rma_location-9.0.1.0.0.dist-info/DESCRIPTION.rst
odoo9_addon_crm_rma_location-9.0.1.0.0.dist-info/METADATA
odoo9_addon_crm_rma_location-9.0.1.0.0.dist-info/namespace_packages.txt
